asyncio_thread_runner.py
asyncio_thread_runner-1.0.dist-info/licenses/LICENSE
asyncio_thread_runner-1.0.dist-info/WHEEL
asyncio_thread_runner-1.0.dist-info/METADATA
asyncio_thread_runner-1.0.dist-info/RECORD
