Metadata-Version: 2.4
Name: asyncio-thread-runner
Version: 1.0
Summary: Run async code from sync code.
Keywords: async,sync,asyncio,runner,thread
Author: lemon24
Requires-Python: >=3.11
License-Expression: BSD-3-Clause
Classifier: Development Status :: 5 - Production/Stable
Classifier: Framework :: AsyncIO
Classifier: Intended Audience :: Developers
Classifier: Operating System :: OS Independent
Classifier: Programming Language :: Python
Classifier: Programming Language :: Python :: 3
Classifier: Programming Language :: Python :: 3 :: Only
Classifier: Programming Language :: Python :: 3.11
Classifier: Programming Language :: Python :: 3.12
Classifier: Programming Language :: Python :: 3.13
Classifier: Programming Language :: Python :: 3.14
Classifier: Programming Language :: Python :: Implementation :: CPython
Classifier: Programming Language :: Python :: Implementation :: PyPy
Classifier: Typing :: Typed
License-File: LICENSE
Project-URL: Changelog, https://github.com/lemon24/asyncio-thread-runner/blob/main/CHANGES.md
Project-URL: Documentation, https://github.com/lemon24/asyncio-thread-runner/blob/main/README.md
Project-URL: Issues, https://github.com/lemon24/asyncio-thread-runner/issues
Project-URL: Repository, https://github.com/lemon24/asyncio-thread-runner
